setup.py
ath_hag/__init__.py
ath_hag/one.py
ath_hag/two.py
ath_hagex.egg-info/PKG-INFO
ath_hagex.egg-info/SOURCES.txt
ath_hagex.egg-info/dependency_links.txt
ath_hagex.egg-info/top_level.txt