Metadata-Version: 2.1
Name: ath_hagex
Version: 0.0.1
Summary: My Package
Author: Arti579
Author-email: your@domain.com
